{
  "recipe-name": "Gordon Ramsay's Scrambled Eggs",
  "other-ingredients": [
    "salt",
    "pepper"
  ],
  "url": "https://www.youtube.com/watch?v=PUP7U5vTMM0",
  "portions": 1,
  "description": "",
  "time": 25,
  "in": [
    {
      "n": "bread",
      "q": 1,
      "u": "slice"
    },
    {
      "n": "eggs",
      "q": 3,
      "u": "item"
    },
    {
      "n": "cherry tomatoes",
      "q": 50,
      "u": "g"
    },
    {
      "n": "butter",
      "q": 1,
      "u": "tbs"
    },
    {
      "n": "milk",
      "q": 3,
      "u": "tbs"
    },
    {
      "n": "portobello mushrooms",
      "q": 1,
      "u": "item"
    },
    {
      "n": "chives",
      "q": 1,
      "u": "tbs"
    }
  ]
}